datadog_http_handler/__init__.py
datadog_http_handler/formatter.py
datadog_http_handler/handler.py
datadog_http_handler/py.typed
datadog_async_handler-0.1.3.dist-info/METADATA
datadog_async_handler-0.1.3.dist-info/WHEEL
datadog_async_handler-0.1.3.dist-info/licenses/LICENSE
datadog_async_handler-0.1.3.dist-info/RECORD
