Metadata-Version: 2.4
Name: datadog-async-handler
Version: 0.1.3
Summary: High-performance async HTTP logging handler for Datadog with batching and retry logic
Project-URL: Homepage, https://github.com/enlyft/datadog-async-handler
Project-URL: Documentation, https://enlyft.github.io/datadog-async-handler
Project-URL: Repository, https://github.com/enlyft/datadog-async-handler.git
Project-URL: Changelog, https://github.com/enlyft/datadog-async-handler/blob/main/CHANGELOG.md
Project-URL: Bug Tracker, https://github.com/enlyft/datadog-async-handler/issues
Author-email: Parth <parth@enlyft.com>
Maintainer-email: Parth <parth@enlyft.com>
License-Expression: MIT
License-File: LICENSE
Keywords: async,batching,datadog,handler,logging,observability
Classifier: Development Status :: 4 - Beta
Classifier: Intended Audience :: Developers
Classifier: License :: OSI Approved :: MIT License
Classifier: Operating System :: OS Independent
Classifier: Programming Language :: Python :: 3
Classifier: Programming Language :: Python :: 3.9
Classifier: Programming Language :: Python :: 3.10
Classifier: Programming Language :: Python :: 3.11
Classifier: Programming Language :: Python :: 3.12
Classifier: Programming Language :: Python :: 3.13
Classifier: Topic :: Software Development :: Libraries :: Python Modules
Classifier: Topic :: System :: Logging
Classifier: Topic :: System :: Monitoring
Requires-Python: >=3.9
Requires-Dist: datadog-api-client<3.0.0,>=2.0.0
Provides-Extra: async
Requires-Dist: aiohttp>=3.8.0; extra == 'async'
Provides-Extra: dev
Requires-Dist: mypy>=1.8.0; extra == 'dev'
Requires-Dist: pre-commit>=3.6.0; extra == 'dev'
Requires-Dist: pytest-asyncio>=0.23.0; extra == 'dev'
Requires-Dist: pytest-benchmark>=4.0.0; extra == 'dev'
Requires-Dist: pytest-cov>=4.0.0; extra == 'dev'
Requires-Dist: pytest-mock>=3.12.0; extra == 'dev'
Requires-Dist: pytest>=8.0.0; extra == 'dev'
Requires-Dist: ruff>=0.2.0; extra == 'dev'
Requires-Dist: tox>=4.0.0; extra == 'dev'
Provides-Extra: docs
Requires-Dist: mkdocs-material>=9.5.0; extra == 'docs'
Requires-Dist: mkdocs>=1.5.0; extra == 'docs'
Requires-Dist: mkdocstrings[python]>=0.24.0; extra == 'docs'
Provides-Extra: test
Requires-Dist: pytest-asyncio>=0.23.0; extra == 'test'
Requires-Dist: pytest-benchmark>=4.0.0; extra == 'test'
Requires-Dist: pytest-cov>=4.0.0; extra == 'test'
Requires-Dist: pytest-mock>=3.12.0; extra == 'test'
Requires-Dist: pytest>=8.0.0; extra == 'test'
